H_PDF_2_Anki_FCards/Highlighted_PDF_2_Anki_FlashCards.py
H_PDF_2_Anki_FCards/__init__.py
H_PDF_2_Anki_FCards/__main__.py
H_PDF_2_Anki_FCards/f.py
Highlighted_PDF_2_Anki_FlashCards-1.0.1.dist-info/LICENSE
Highlighted_PDF_2_Anki_FlashCards-1.0.1.dist-info/METADATA
Highlighted_PDF_2_Anki_FlashCards-1.0.1.dist-info/WHEEL
Highlighted_PDF_2_Anki_FlashCards-1.0.1.dist-info/entry_points.txt
Highlighted_PDF_2_Anki_FlashCards-1.0.1.dist-info/top_level.txt
Highlighted_PDF_2_Anki_FlashCards-1.0.1.dist-info/RECORD
