Metadata-Version: 2.1
Name: Highlighted_PDF_2_Anki_FlashCards
Version: 1.0.1
Summary: No description yet
Author-email: Ali Jalaali <a.jalali.248@gmail.com>
License: Copyright (c) 2018 The Python Packaging Authority
Project-URL: Homepage, https://github.com/Jal-Ali/Highlighted_PDF_2_Anki_FlashCards
Keywords: Anki
Classifier: License :: OSI Approved :: MIT License
Classifier: Programming Language :: Python
Classifier: Programming Language :: Python :: 3
License-File: LICENSE
Requires-Dist: googletrans
Requires-Dist: PyMuPDF
Requires-Dist: PyQt6
